mul.recipe.appengine-0.4.0-py2.7-nspkg.pth
mul/recipe/appengine/__init__.py
mul/recipe/appengine/lib.py
mul/recipe/appengine/sdk.py
mul.recipe.appengine-0.4.0.dist-info/DESCRIPTION.rst
mul.recipe.appengine-0.4.0.dist-info/entry_points.txt
mul.recipe.appengine-0.4.0.dist-info/METADATA
mul.recipe.appengine-0.4.0.dist-info/metadata.json
mul.recipe.appengine-0.4.0.dist-info/namespace_packages.txt
mul.recipe.appengine-0.4.0.dist-info/RECORD
mul.recipe.appengine-0.4.0.dist-info/top_level.txt
mul.recipe.appengine-0.4.0.dist-info/WHEEL
