Metadata-Version: 2.0
Name: mul.recipe.appengine
Version: 0.4.0
Summary: Buildout recipes for App Engine.
Home-page: https://github.com/michaellenaghan/mul.recipe.appengine
Author: Michael Lenaghan
Author-email: metamul -@- gmail.com
License: BSD
Keywords: app appengine buildout engine gae mul recipe zc.buildout
Platform: UNKNOWN
Classifier: Development Status :: 2 - Pre-Alpha
Classifier: Framework :: Buildout
Classifier: Intended Audience :: Developers
Classifier: License :: OSI Approved :: BSD License
Classifier: Natural Language :: English
Classifier: Programming Language :: Python :: 2
Classifier: Programming Language :: Python :: 2.7
Requires-Dist: setuptools (>=8.0)
Requires-Dist: zc.buildout (>=2.3.1)
Requires-Dist: zc.recipe.egg (>=2.0.1)
